{
  "index": "/index.html",
  "assetGroups": [{
    "name": "app",
    "installMode": "prefetch",
    "resources": {
      "files": [
        "/favicon.ico",
        "/index.html"
      ],
      "versionedFiles": [
        "/*.bundle.css",
        "/*.bundle.js",
        "/*.chunk.js"
      ]
    }
  }, {
    "name": "assets",
    "installMode": "lazy",
    "updateMode": "prefetch",
    "resources": {
      "files": [
        "/assets/**"
      ],
      "urls": [
        "/contacts",
        "/settings"
      ]
    }
  }],
  "dataGroups": [{
    "name": "api-freshness",
    "urls": [
      "/contact/**",
      "/contact/groups",
      "/contacts",
      "/zone/social_network/notifications/get_new_notifications/count",
      "/chat/notification/count"
    ],
    "cacheConfig": {
      "maxSize": 30,
      "maxAge": "7d",
      "timeout": "60s",
      "strategy": "freshness"
    }
  },
    {
      "name": "api-performance",
      "urls": [
        "/settings"
      ],
      "cacheConfig": {
        "maxSize": 30,
        "maxAge": "7d",
        "timeout": "60s",
        "strategy": "performance"
      }
    }]
}
